<RuleSet xmlns="http://www.thepalladiumgroup.com/paf_rule_set">
  <type>0</type>
  <name>RePlanning</name>
  <measureList>
    <string>accounts</string>
    <string>sales_spti</string>
    <string>sales_spte</string>
    <string>vat_%</string>
    <string>actioned_md_spti</string>
    <string>actioned_md%_spti</string>
    <string>csm</string>
    <string>csm%_spte</string>
    <string>clearance</string>
    <string>pchange_up</string>
    <string>pchange_down</string>
    <string>pos</string>
    <string>other</string>
    <string>promo</string>
    <string>clearance_%</string>
    <string>pchange_up_%</string>
    <string>pchange_down_%</string>
    <string>pos_%</string>
    <string>other_%</string>
    <string>promo_%</string>
    <string>intake_%_del</string>
    <string>intake_del</string>
    <string>intake_%_fcst</string>
    <string>intake_fcst</string>
    <string>intake_%_tot</string>
    <string>intake_tot</string>
    <string>intake_margin</string>
    <string>needed_intake</string>
    <string>commitment_spti</string>
    <string>commitment_spte</string>
    <string>commitment_cpte</string>
  </measureList>
  <ruleGroups>
    <RuleGroup>
      <rules>
        <Rule>
          <formula>
            <resultTerm>actioned_md_spti</resultTerm>
            <expression>sales_spti * actioned_md%_spti</expression>
            <resultFunction>false</resultFunction>
            <isParsed>false</isParsed>
          </formula>
          <key>0</key>
          <baseAllocateMeasure>sales_spti</baseAllocateMeasure>
          <skipAllocation>false</skipAllocation>
          <lockAllocation>false</lockAllocation>
          <skipAggregation>false</skipAggregation>
          <lockSystemEvaluationResult>false</lockSystemEvaluationResult>
          <lockUserEvaluationResult>false</lockUserEvaluationResult>
          <evalLockedIntersections>false</evalLockedIntersections>
          <lockAllPriorTime>false</lockAllPriorTime>
          <calcAllPeriods>false</calcAllPeriods>
          <initialTBFirstAllocation>false</initialTBFirstAllocation>
        </Rule>
      </rules>
      <perpetual>false</perpetual>
      <delayedPerpetual>false</delayedPerpetual>
      <perpetualAllocation>false</perpetualAllocation>
      <skipProtProc>true</skipProtProc>
      <performInitialAllocation>false</performInitialAllocation>
    </RuleGroup>
    <RuleGroup>
      <rules>
        <Rule>
          <formula>
            <resultTerm>clearance</resultTerm>
            <expression>sales_spti * clearance_%</expression>
            <resultFunction>false</resultFunction>
            <isParsed>false</isParsed>
          </formula>
          <key>0</key>
          <baseAllocateMeasure>sales_spti</baseAllocateMeasure>
          <skipAllocation>false</skipAllocation>
          <lockAllocation>false</lockAllocation>
          <skipAggregation>false</skipAggregation>
          <lockSystemEvaluationResult>false</lockSystemEvaluationResult>
          <lockUserEvaluationResult>false</lockUserEvaluationResult>
          <evalLockedIntersections>false</evalLockedIntersections>
          <lockAllPriorTime>false</lockAllPriorTime>
          <calcAllPeriods>false</calcAllPeriods>
          <initialTBFirstAllocation>false</initialTBFirstAllocation>
        </Rule>
      </rules>
      <perpetual>false</perpetual>
      <delayedPerpetual>false</delayedPerpetual>
      <perpetualAllocation>false</perpetualAllocation>
      <skipProtProc>true</skipProtProc>
      <performInitialAllocation>false</performInitialAllocation>
    </RuleGroup>
    <RuleGroup>
      <rules>
        <Rule>
          <formula>
            <resultTerm>promo</resultTerm>
            <expression>sales_spti * promo_%</expression>
            <resultFunction>false</resultFunction>
            <isParsed>false</isParsed>
          </formula>
          <key>0</key>
          <baseAllocateMeasure>sales_spti</baseAllocateMeasure>
          <skipAllocation>false</skipAllocation>
          <lockAllocation>false</lockAllocation>
          <skipAggregation>false</skipAggregation>
          <lockSystemEvaluationResult>false</lockSystemEvaluationResult>
          <lockUserEvaluationResult>false</lockUserEvaluationResult>
          <evalLockedIntersections>false</evalLockedIntersections>
          <lockAllPriorTime>false</lockAllPriorTime>
          <calcAllPeriods>false</calcAllPeriods>
          <initialTBFirstAllocation>false</initialTBFirstAllocation>
        </Rule>
        <Rule>
          <formula>
            <resultTerm>promo_%</resultTerm>
            <expression>promo / sales_spti</expression>
            <resultFunction>false</resultFunction>
            <isParsed>false</isParsed>
          </formula>
          <key>0</key>
          <skipAllocation>false</skipAllocation>
          <lockAllocation>false</lockAllocation>
          <skipAggregation>false</skipAggregation>
          <lockSystemEvaluationResult>false</lockSystemEvaluationResult>
          <lockUserEvaluationResult>false</lockUserEvaluationResult>
          <evalLockedIntersections>false</evalLockedIntersections>
          <lockAllPriorTime>false</lockAllPriorTime>
          <calcAllPeriods>false</calcAllPeriods>
          <initialTBFirstAllocation>false</initialTBFirstAllocation>
        </Rule>
      </rules>
      <perpetual>false</perpetual>
      <delayedPerpetual>false</delayedPerpetual>
      <perpetualAllocation>false</perpetualAllocation>
      <skipProtProc>false</skipProtProc>
      <performInitialAllocation>false</performInitialAllocation>
    </RuleGroup>
    <RuleGroup>
      <rules>
        <Rule>
          <formula>
            <resultTerm>pchange_up</resultTerm>
            <expression>sales_spti * pchange_up_%</expression>
            <resultFunction>false</resultFunction>
            <isParsed>false</isParsed>
          </formula>
          <key>0</key>
          <baseAllocateMeasure>sales_spti</baseAllocateMeasure>
          <skipAllocation>false</skipAllocation>
          <lockAllocation>false</lockAllocation>
          <skipAggregation>false</skipAggregation>
          <lockSystemEvaluationResult>false</lockSystemEvaluationResult>
          <lockUserEvaluationResult>false</lockUserEvaluationResult>
          <evalLockedIntersections>false</evalLockedIntersections>
          <lockAllPriorTime>false</lockAllPriorTime>
          <calcAllPeriods>false</calcAllPeriods>
          <initialTBFirstAllocation>false</initialTBFirstAllocation>
        </Rule>
        <Rule>
          <formula>
            <resultTerm>pchange_up_%</resultTerm>
            <expression>pchange_up / sales_spti</expression>
            <resultFunction>false</resultFunction>
            <isParsed>false</isParsed>
          </formula>
          <key>0</key>
          <skipAllocation>false</skipAllocation>
          <lockAllocation>false</lockAllocation>
          <skipAggregation>false</skipAggregation>
          <lockSystemEvaluationResult>false</lockSystemEvaluationResult>
          <lockUserEvaluationResult>false</lockUserEvaluationResult>
          <evalLockedIntersections>false</evalLockedIntersections>
          <lockAllPriorTime>false</lockAllPriorTime>
          <calcAllPeriods>false</calcAllPeriods>
          <initialTBFirstAllocation>false</initialTBFirstAllocation>
        </Rule>
      </rules>
      <perpetual>false</perpetual>
      <delayedPerpetual>false</delayedPerpetual>
      <perpetualAllocation>false</perpetualAllocation>
      <skipProtProc>false</skipProtProc>
      <performInitialAllocation>false</performInitialAllocation>
    </RuleGroup>
    <RuleGroup>
      <rules>
        <Rule>
          <formula>
            <resultTerm>pchange_down</resultTerm>
            <expression>sales_spti * pchange_down_%</expression>
            <resultFunction>false</resultFunction>
            <isParsed>false</isParsed>
          </formula>
          <key>0</key>
          <baseAllocateMeasure>sales_spti</baseAllocateMeasure>
          <skipAllocation>false</skipAllocation>
          <lockAllocation>false</lockAllocation>
          <skipAggregation>false</skipAggregation>
          <lockSystemEvaluationResult>false</lockSystemEvaluationResult>
          <lockUserEvaluationResult>false</lockUserEvaluationResult>
          <evalLockedIntersections>false</evalLockedIntersections>
          <lockAllPriorTime>false</lockAllPriorTime>
          <calcAllPeriods>false</calcAllPeriods>
          <initialTBFirstAllocation>false</initialTBFirstAllocation>
        </Rule>
        <Rule>
          <formula>
            <resultTerm>pchange_down_%</resultTerm>
            <expression>pchange_down / sales_spti</expression>
            <resultFunction>false</resultFunction>
            <isParsed>false</isParsed>
          </formula>
          <key>0</key>
          <skipAllocation>false</skipAllocation>
          <lockAllocation>false</lockAllocation>
          <skipAggregation>false</skipAggregation>
          <lockSystemEvaluationResult>false</lockSystemEvaluationResult>
          <lockUserEvaluationResult>false</lockUserEvaluationResult>
          <evalLockedIntersections>false</evalLockedIntersections>
          <lockAllPriorTime>false</lockAllPriorTime>
          <calcAllPeriods>false</calcAllPeriods>
          <initialTBFirstAllocation>false</initialTBFirstAllocation>
        </Rule>
      </rules>
      <perpetual>false</perpetual>
      <delayedPerpetual>false</delayedPerpetual>
      <perpetualAllocation>false</perpetualAllocation>
      <skipProtProc>false</skipProtProc>
      <performInitialAllocation>false</performInitialAllocation>
    </RuleGroup>
    <RuleGroup>
      <rules>
        <Rule>
          <formula>
            <resultTerm>pos</resultTerm>
            <expression>sales_spti * pos_%</expression>
            <resultFunction>false</resultFunction>
            <isParsed>false</isParsed>
          </formula>
          <key>0</key>
          <baseAllocateMeasure>sales_spti</baseAllocateMeasure>
          <skipAllocation>false</skipAllocation>
          <lockAllocation>false</lockAllocation>
          <skipAggregation>false</skipAggregation>
          <lockSystemEvaluationResult>false</lockSystemEvaluationResult>
          <lockUserEvaluationResult>false</lockUserEvaluationResult>
          <evalLockedIntersections>false</evalLockedIntersections>
          <lockAllPriorTime>false</lockAllPriorTime>
          <calcAllPeriods>false</calcAllPeriods>
          <initialTBFirstAllocation>false</initialTBFirstAllocation>
        </Rule>
        <Rule>
          <formula>
            <resultTerm>pos_%</resultTerm>
            <expression>pos / sales_spti</expression>
            <resultFunction>false</resultFunction>
            <isParsed>false</isParsed>
          </formula>
          <key>0</key>
          <skipAllocation>false</skipAllocation>
          <lockAllocation>false</lockAllocation>
          <skipAggregation>false</skipAggregation>
          <lockSystemEvaluationResult>false</lockSystemEvaluationResult>
          <lockUserEvaluationResult>false</lockUserEvaluationResult>
          <evalLockedIntersections>false</evalLockedIntersections>
          <lockAllPriorTime>false</lockAllPriorTime>
          <calcAllPeriods>false</calcAllPeriods>
          <initialTBFirstAllocation>false</initialTBFirstAllocation>
        </Rule>
      </rules>
      <perpetual>false</perpetual>
      <delayedPerpetual>false</delayedPerpetual>
      <perpetualAllocation>false</perpetualAllocation>
      <skipProtProc>false</skipProtProc>
      <performInitialAllocation>false</performInitialAllocation>
    </RuleGroup>
    <RuleGroup>
      <rules>
        <Rule>
          <formula>
            <resultTerm>other</resultTerm>
            <expression>sales_spti * other_%</expression>
            <resultFunction>false</resultFunction>
            <isParsed>false</isParsed>
          </formula>
          <key>0</key>
          <baseAllocateMeasure>sales_spti</baseAllocateMeasure>
          <skipAllocation>false</skipAllocation>
          <lockAllocation>false</lockAllocation>
          <skipAggregation>false</skipAggregation>
          <lockSystemEvaluationResult>false</lockSystemEvaluationResult>
          <lockUserEvaluationResult>false</lockUserEvaluationResult>
          <evalLockedIntersections>false</evalLockedIntersections>
          <lockAllPriorTime>false</lockAllPriorTime>
          <calcAllPeriods>false</calcAllPeriods>
          <initialTBFirstAllocation>false</initialTBFirstAllocation>
        </Rule>
        <Rule>
          <formula>
            <resultTerm>other_%</resultTerm>
            <expression>other / sales_spti</expression>
            <resultFunction>false</resultFunction>
            <isParsed>false</isParsed>
          </formula>
          <key>0</key>
          <skipAllocation>false</skipAllocation>
          <lockAllocation>false</lockAllocation>
          <skipAggregation>false</skipAggregation>
          <lockSystemEvaluationResult>false</lockSystemEvaluationResult>
          <lockUserEvaluationResult>false</lockUserEvaluationResult>
          <evalLockedIntersections>false</evalLockedIntersections>
          <lockAllPriorTime>false</lockAllPriorTime>
          <calcAllPeriods>false</calcAllPeriods>
          <initialTBFirstAllocation>false</initialTBFirstAllocation>
        </Rule>
      </rules>
      <perpetual>false</perpetual>
      <delayedPerpetual>false</delayedPerpetual>
      <perpetualAllocation>false</perpetualAllocation>
      <skipProtProc>false</skipProtProc>
      <performInitialAllocation>false</performInitialAllocation>
    </RuleGroup>
    <RuleGroup>
      <rules>
        <Rule>
          <formula>
            <resultTerm>actioned_md_spti</resultTerm>
            <expression>clearance + promo + pchange_up + pchange_down + pos + other</expression>
            <resultFunction>false</resultFunction>
            <isParsed>false</isParsed>
          </formula>
          <key>0</key>
          <baseAllocateMeasure>sales_spti</baseAllocateMeasure>
          <skipAllocation>false</skipAllocation>
          <lockAllocation>false</lockAllocation>
          <skipAggregation>false</skipAggregation>
          <lockSystemEvaluationResult>false</lockSystemEvaluationResult>
          <lockUserEvaluationResult>false</lockUserEvaluationResult>
          <evalLockedIntersections>false</evalLockedIntersections>
          <lockAllPriorTime>false</lockAllPriorTime>
          <calcAllPeriods>false</calcAllPeriods>
          <initialTBFirstAllocation>false</initialTBFirstAllocation>
        </Rule>
        <Rule>
          <formula>
            <resultTerm>clearance</resultTerm>
            <expression>actioned_md_spti - promo - pchange_up - pchange_down - pos - other</expression>
            <resultFunction>false</resultFunction>
            <isParsed>false</isParsed>
          </formula>
          <key>0</key>
          <skipAllocation>false</skipAllocation>
          <lockAllocation>false</lockAllocation>
          <skipAggregation>false</skipAggregation>
          <lockSystemEvaluationResult>false</lockSystemEvaluationResult>
          <lockUserEvaluationResult>false</lockUserEvaluationResult>
          <evalLockedIntersections>false</evalLockedIntersections>
          <lockAllPriorTime>false</lockAllPriorTime>
          <calcAllPeriods>false</calcAllPeriods>
          <initialTBFirstAllocation>false</initialTBFirstAllocation>
        </Rule>
      </rules>
      <perpetual>false</perpetual>
      <delayedPerpetual>false</delayedPerpetual>
      <perpetualAllocation>false</perpetualAllocation>
      <skipProtProc>false</skipProtProc>
      <performInitialAllocation>false</performInitialAllocation>
    </RuleGroup>
    <RuleGroup>
      <rules>
        <Rule>
          <formula>
            <resultTerm>actioned_md%_spti</resultTerm>
            <expression>actioned_md_spti / sales_spti</expression>
            <resultFunction>false</resultFunction>
            <isParsed>false</isParsed>
          </formula>
          <key>0</key>
          <skipAllocation>false</skipAllocation>
          <lockAllocation>false</lockAllocation>
          <skipAggregation>false</skipAggregation>
          <lockSystemEvaluationResult>false</lockSystemEvaluationResult>
          <lockUserEvaluationResult>false</lockUserEvaluationResult>
          <evalLockedIntersections>false</evalLockedIntersections>
          <lockAllPriorTime>false</lockAllPriorTime>
          <calcAllPeriods>false</calcAllPeriods>
          <initialTBFirstAllocation>false</initialTBFirstAllocation>
        </Rule>
        <Rule>
          <formula>
            <resultTerm>actioned_md_spti</resultTerm>
            <expression>sales_spti * actioned_md%_spti</expression>
            <resultFunction>false</resultFunction>
            <isParsed>false</isParsed>
          </formula>
          <key>0</key>
          <baseAllocateMeasure>sales_spti</baseAllocateMeasure>
          <skipAllocation>false</skipAllocation>
          <lockAllocation>false</lockAllocation>
          <skipAggregation>false</skipAggregation>
          <lockSystemEvaluationResult>false</lockSystemEvaluationResult>
          <lockUserEvaluationResult>false</lockUserEvaluationResult>
          <evalLockedIntersections>false</evalLockedIntersections>
          <lockAllPriorTime>false</lockAllPriorTime>
          <calcAllPeriods>false</calcAllPeriods>
          <initialTBFirstAllocation>false</initialTBFirstAllocation>
        </Rule>
      </rules>
      <perpetual>false</perpetual>
      <delayedPerpetual>false</delayedPerpetual>
      <perpetualAllocation>false</perpetualAllocation>
      <skipProtProc>false</skipProtProc>
      <performInitialAllocation>false</performInitialAllocation>
    </RuleGroup>
    <RuleGroup>
      <rules>
        <Rule>
          <formula>
            <resultTerm>clearance_%</resultTerm>
            <expression>clearance / sales_spti</expression>
            <resultFunction>false</resultFunction>
            <isParsed>false</isParsed>
          </formula>
          <key>0</key>
          <skipAllocation>false</skipAllocation>
          <lockAllocation>false</lockAllocation>
          <skipAggregation>false</skipAggregation>
          <lockSystemEvaluationResult>false</lockSystemEvaluationResult>
          <lockUserEvaluationResult>false</lockUserEvaluationResult>
          <evalLockedIntersections>false</evalLockedIntersections>
          <lockAllPriorTime>false</lockAllPriorTime>
          <calcAllPeriods>false</calcAllPeriods>
          <initialTBFirstAllocation>false</initialTBFirstAllocation>
        </Rule>
        <Rule>
          <formula>
            <resultTerm>clearance</resultTerm>
            <expression>sales_spti * clearance_%</expression>
            <resultFunction>false</resultFunction>
            <isParsed>false</isParsed>
          </formula>
          <key>0</key>
          <skipAllocation>false</skipAllocation>
          <lockAllocation>false</lockAllocation>
          <skipAggregation>false</skipAggregation>
          <lockSystemEvaluationResult>false</lockSystemEvaluationResult>
          <lockUserEvaluationResult>false</lockUserEvaluationResult>
          <evalLockedIntersections>false</evalLockedIntersections>
          <lockAllPriorTime>false</lockAllPriorTime>
          <calcAllPeriods>false</calcAllPeriods>
          <initialTBFirstAllocation>false</initialTBFirstAllocation>
        </Rule>
      </rules>
      <perpetual>false</perpetual>
      <delayedPerpetual>false</delayedPerpetual>
      <perpetualAllocation>false</perpetualAllocation>
      <skipProtProc>false</skipProtProc>
      <performInitialAllocation>false</performInitialAllocation>
    </RuleGroup>
    <RuleGroup>
      <rules>
        <Rule>
          <formula>
            <resultTerm>sales_spte</resultTerm>
            <expression>sales_spti / (1 + @BOP(vat_%))</expression>
            <resultFunction>false</resultFunction>
            <isParsed>false</isParsed>
          </formula>
          <key>0</key>
          <skipAllocation>false</skipAllocation>
          <lockAllocation>false</lockAllocation>
          <skipAggregation>false</skipAggregation>
          <lockSystemEvaluationResult>false</lockSystemEvaluationResult>
          <lockUserEvaluationResult>false</lockUserEvaluationResult>
          <evalLockedIntersections>false</evalLockedIntersections>
          <lockAllPriorTime>false</lockAllPriorTime>
          <calcAllPeriods>false</calcAllPeriods>
          <initialTBFirstAllocation>false</initialTBFirstAllocation>
        </Rule>
        <Rule>
          <formula>
            <resultTerm>vat_%</resultTerm>
            <expression>@IF((sales_spti - sales_spte) = 0, vat_%, (sales_spti - sales_spte) / sales_spte)</expression>
            <resultFunction>false</resultFunction>
            <isParsed>false</isParsed>
          </formula>
          <key>0</key>
          <skipAllocation>false</skipAllocation>
          <lockAllocation>false</lockAllocation>
          <skipAggregation>false</skipAggregation>
          <lockSystemEvaluationResult>false</lockSystemEvaluationResult>
          <lockUserEvaluationResult>false</lockUserEvaluationResult>
          <evalLockedIntersections>false</evalLockedIntersections>
          <lockAllPriorTime>false</lockAllPriorTime>
          <calcAllPeriods>false</calcAllPeriods>
          <initialTBFirstAllocation>false</initialTBFirstAllocation>
        </Rule>
      </rules>
      <perpetual>true</perpetual>
      <delayedPerpetual>false</delayedPerpetual>
      <perpetualAllocation>false</perpetualAllocation>
      <skipProtProc>false</skipProtProc>
      <performInitialAllocation>false</performInitialAllocation>
    </RuleGroup>
    <RuleGroup>
      <rules>
        <Rule>
          <formula>
            <resultTerm>commitment_spti</resultTerm>
            <expression>intake_del * intake_%_del</expression>
            <resultFunction>false</resultFunction>
            <isParsed>false</isParsed>
          </formula>
          <key>0</key>
          <skipAllocation>false</skipAllocation>
          <lockAllocation>false</lockAllocation>
          <skipAggregation>false</skipAggregation>
          <lockSystemEvaluationResult>false</lockSystemEvaluationResult>
          <lockUserEvaluationResult>false</lockUserEvaluationResult>
          <evalLockedIntersections>false</evalLockedIntersections>
          <lockAllPriorTime>false</lockAllPriorTime>
          <calcAllPeriods>false</calcAllPeriods>
          <initialTBFirstAllocation>false</initialTBFirstAllocation>
        </Rule>
        <Rule>
          <formula>
            <resultTerm>intake_%_del</resultTerm>
            <expression>@IF(intake_del = 0, intake_%_del, (commitment_spte - commitment_cpte) / commitment_spte)</expression>
            <resultFunction>false</resultFunction>
            <isParsed>false</isParsed>
          </formula>
          <key>0</key>
          <skipAllocation>false</skipAllocation>
          <lockAllocation>false</lockAllocation>
          <skipAggregation>false</skipAggregation>
          <lockSystemEvaluationResult>false</lockSystemEvaluationResult>
          <lockUserEvaluationResult>false</lockUserEvaluationResult>
          <evalLockedIntersections>false</evalLockedIntersections>
          <lockAllPriorTime>false</lockAllPriorTime>
          <calcAllPeriods>false</calcAllPeriods>
          <initialTBFirstAllocation>false</initialTBFirstAllocation>
        </Rule>
      </rules>
      <perpetual>false</perpetual>
      <delayedPerpetual>false</delayedPerpetual>
      <perpetualAllocation>false</perpetualAllocation>
      <skipProtProc>false</skipProtProc>
      <performInitialAllocation>false</performInitialAllocation>
    </RuleGroup>
    <RuleGroup>
      <rules>
        <Rule>
          <formula>
            <resultTerm>needed_intake</resultTerm>
            <expression>intake_fcst * intake_%_fcst</expression>
            <resultFunction>false</resultFunction>
            <isParsed>false</isParsed>
          </formula>
          <key>0</key>
          <skipAllocation>false</skipAllocation>
          <lockAllocation>false</lockAllocation>
          <skipAggregation>false</skipAggregation>
          <lockSystemEvaluationResult>false</lockSystemEvaluationResult>
          <lockUserEvaluationResult>false</lockUserEvaluationResult>
          <evalLockedIntersections>false</evalLockedIntersections>
          <lockAllPriorTime>false</lockAllPriorTime>
          <calcAllPeriods>false</calcAllPeriods>
          <initialTBFirstAllocation>false</initialTBFirstAllocation>
        </Rule>
        <Rule>
          <formula>
            <resultTerm>intake_%_fcst</resultTerm>
            <expression>@IF(intake_fcst = 0, intake_%_fcst, needed_intake / intake_fcst)</expression>
            <resultFunction>false</resultFunction>
            <isParsed>false</isParsed>
          </formula>
          <key>0</key>
          <skipAllocation>false</skipAllocation>
          <lockAllocation>false</lockAllocation>
          <skipAggregation>false</skipAggregation>
          <lockSystemEvaluationResult>false</lockSystemEvaluationResult>
          <lockUserEvaluationResult>false</lockUserEvaluationResult>
          <evalLockedIntersections>false</evalLockedIntersections>
          <lockAllPriorTime>false</lockAllPriorTime>
          <calcAllPeriods>false</calcAllPeriods>
          <initialTBFirstAllocation>false</initialTBFirstAllocation>
        </Rule>
      </rules>
      <perpetual>false</perpetual>
      <delayedPerpetual>false</delayedPerpetual>
      <perpetualAllocation>false</perpetualAllocation>
      <skipProtProc>false</skipProtProc>
      <performInitialAllocation>false</performInitialAllocation>
    </RuleGroup>
    <RuleGroup>
      <rules>
        <Rule>
          <formula>
            <resultTerm>intake_tot</resultTerm>
            <expression>intake_fcst + intake_del</expression>
            <resultFunction>false</resultFunction>
            <isParsed>false</isParsed>
          </formula>
          <key>0</key>
          <skipAllocation>false</skipAllocation>
          <lockAllocation>false</lockAllocation>
          <skipAggregation>false</skipAggregation>
          <lockSystemEvaluationResult>false</lockSystemEvaluationResult>
          <lockUserEvaluationResult>false</lockUserEvaluationResult>
          <evalLockedIntersections>false</evalLockedIntersections>
          <lockAllPriorTime>false</lockAllPriorTime>
          <calcAllPeriods>false</calcAllPeriods>
          <initialTBFirstAllocation>false</initialTBFirstAllocation>
        </Rule>
      </rules>
      <perpetual>false</perpetual>
      <delayedPerpetual>false</delayedPerpetual>
      <perpetualAllocation>false</perpetualAllocation>
      <skipProtProc>false</skipProtProc>
      <performInitialAllocation>false</performInitialAllocation>
    </RuleGroup>
    <RuleGroup>
      <rules>
        <Rule>
          <formula>
            <resultTerm>intake_margin</resultTerm>
            <expression>needed_intake + commitment_spti</expression>
            <resultFunction>false</resultFunction>
            <isParsed>false</isParsed>
          </formula>
          <key>0</key>
          <skipAllocation>false</skipAllocation>
          <lockAllocation>false</lockAllocation>
          <skipAggregation>false</skipAggregation>
          <lockSystemEvaluationResult>false</lockSystemEvaluationResult>
          <lockUserEvaluationResult>false</lockUserEvaluationResult>
          <evalLockedIntersections>false</evalLockedIntersections>
          <lockAllPriorTime>false</lockAllPriorTime>
          <calcAllPeriods>false</calcAllPeriods>
          <initialTBFirstAllocation>false</initialTBFirstAllocation>
        </Rule>
      </rules>
      <perpetual>false</perpetual>
      <delayedPerpetual>false</delayedPerpetual>
      <perpetualAllocation>false</perpetualAllocation>
      <skipProtProc>false</skipProtProc>
      <performInitialAllocation>false</performInitialAllocation>
    </RuleGroup>
    <RuleGroup>
      <rules>
        <Rule>
          <formula>
            <resultTerm>intake_%_tot</resultTerm>
            <expression>intake_margin / intake_tot</expression>
            <resultFunction>false</resultFunction>
            <isParsed>false</isParsed>
          </formula>
          <key>0</key>
          <skipAllocation>false</skipAllocation>
          <lockAllocation>false</lockAllocation>
          <skipAggregation>false</skipAggregation>
          <lockSystemEvaluationResult>false</lockSystemEvaluationResult>
          <lockUserEvaluationResult>false</lockUserEvaluationResult>
          <evalLockedIntersections>false</evalLockedIntersections>
          <lockAllPriorTime>false</lockAllPriorTime>
          <calcAllPeriods>false</calcAllPeriods>
          <initialTBFirstAllocation>false</initialTBFirstAllocation>
        </Rule>
      </rules>
      <perpetual>false</perpetual>
      <delayedPerpetual>false</delayedPerpetual>
      <perpetualAllocation>false</perpetualAllocation>
      <skipProtProc>false</skipProtProc>
      <performInitialAllocation>false</performInitialAllocation>
    </RuleGroup>
    <RuleGroup>
      <rules>
        <Rule>
          <formula>
            <resultTerm>csm</resultTerm>
            <expression>(sales_spte * @BOP(intake_%_tot)) - (((1-@BOP(intake_%_tot))* actioned_md_spti) / (1+@BOP(vat_%)))</expression>
            <resultFunction>false</resultFunction>
            <isParsed>false</isParsed>
          </formula>
          <key>0</key>
          <skipAllocation>false</skipAllocation>
          <lockAllocation>false</lockAllocation>
          <skipAggregation>false</skipAggregation>
          <lockSystemEvaluationResult>false</lockSystemEvaluationResult>
          <lockUserEvaluationResult>false</lockUserEvaluationResult>
          <evalLockedIntersections>false</evalLockedIntersections>
          <lockAllPriorTime>false</lockAllPriorTime>
          <calcAllPeriods>false</calcAllPeriods>
          <initialTBFirstAllocation>false</initialTBFirstAllocation>
        </Rule>
      </rules>
      <perpetual>true</perpetual>
      <delayedPerpetual>false</delayedPerpetual>
      <perpetualAllocation>false</perpetualAllocation>
      <skipProtProc>false</skipProtProc>
      <performInitialAllocation>false</performInitialAllocation>
    </RuleGroup>
    <RuleGroup>
      <rules>
        <Rule>
          <formula>
            <resultTerm>csm%_spte</resultTerm>
            <expression>csm / sales_spte</expression>
            <resultFunction>false</resultFunction>
            <isParsed>false</isParsed>
          </formula>
          <key>0</key>
          <skipAllocation>false</skipAllocation>
          <lockAllocation>false</lockAllocation>
          <skipAggregation>false</skipAggregation>
          <lockSystemEvaluationResult>false</lockSystemEvaluationResult>
          <lockUserEvaluationResult>false</lockUserEvaluationResult>
          <evalLockedIntersections>false</evalLockedIntersections>
          <lockAllPriorTime>false</lockAllPriorTime>
          <calcAllPeriods>false</calcAllPeriods>
          <initialTBFirstAllocation>false</initialTBFirstAllocation>
        </Rule>
      </rules>
      <perpetual>false</perpetual>
      <delayedPerpetual>false</delayedPerpetual>
      <perpetualAllocation>false</perpetualAllocation>
      <skipProtProc>false</skipProtProc>
      <performInitialAllocation>false</performInitialAllocation>
    </RuleGroup>
  </ruleGroups>
</RuleSet>