<com.palladium.paf.app.UnitOfWork>
  <dimMembers>
    <entry>
      <string>Years</string>
      <string-array>
        <string>FY2006</string>
      </string-array>
    </entry>
    <entry>
      <string>Time</string>
      <string-array>
        <string>S02</string>
        <string>Q3</string>
        <string>Aug</string>
        <string>WK27</string>
        <string>WK28</string>
        <string>WK29</string>
        <string>WK30</string>
        <string>Sep</string>
        <string>WK31</string>
        <string>WK32</string>
        <string>WK33</string>
        <string>WK34</string>
        <string>Oct</string>
        <string>WK35</string>
        <string>WK36</string>
        <string>WK37</string>
        <string>WK38</string>
        <string>WK39</string>
        <string>Q4</string>
        <string>Nov</string>
        <string>WK40</string>
        <string>WK41</string>
        <string>WK42</string>
        <string>WK43</string>
        <string>Dec</string>
        <string>WK44</string>
        <string>WK45</string>
        <string>WK46</string>
        <string>WK47</string>
        <string>Jan</string>
        <string>WK48</string>
        <string>WK49</string>
        <string>WK50</string>
        <string>WK51</string>
        <string>WK52</string>
      </string-array>
    </entry>
    <entry>
      <string>Measures</string>
      <string-array>
        <string>SLS_AUR</string>
        <string>OTB</string>
        <string>MDCLEAR_DLR</string>
        <string>BOPCST_DLR</string>
        <string>RECRTL_APS_DLR</string>
        <string>PROJECTED</string>
        <string>CUMOTBIMU_%</string>
        <string>AVGINVRTL_APS_DLR</string>
        <string>RECCST_DLR</string>
        <string>RECRTL_DLR</string>
        <string>SACCT1</string>
        <string>ACTUAL_ADJ_TTL</string>
        <string>SLS_%_LOC_TOT</string>
        <string>EOP_AUR</string>
        <string>GM_%</string>
        <string>TURN</string>
        <string>SLS_%_LOC_PARENT</string>
        <string>CUMOTB_AUR</string>
        <string>GL</string>
        <string>EOPRTL_DLR</string>
        <string>STORE_COUNT</string>
        <string>EOPIMU_%</string>
        <string>YTDAVAILRTL_DLR</string>
        <string>SLS_%_TIME_PARENT</string>
        <string>ADJ_DLR</string>
        <string>SLS_APS_DLR</string>
        <string>REC_U</string>
        <string>CUMIMU_%</string>
        <string>ADJUST_TTL</string>
        <string>CUMOTB_U</string>
        <string>MDPROMO_%</string>
        <string>ADJ_U</string>
        <string>BLOCKOUT</string>
        <string>SLS_%_PROD_PARENT</string>
        <string>ADJUST</string>
        <string>SLS_%_TIME_TOT</string>
        <string>MDPERM_DLR</string>
        <string>UNAPPROVED_TTL</string>
        <string>AVGINVCST_DLR</string>
        <string>OTB_AUR</string>
        <string>AVGINVRTL_DLR</string>
        <string>BOP_U</string>
        <string>WEEKS_OF_SUPPLY</string>
        <string>EOPCST_DLR</string>
        <string>BOPCST_APS_DLR</string>
        <string>ACTUAL_TTL</string>
        <string>APPROVED</string>
        <string>CANCEL</string>
        <string>OTBIMU_%</string>
        <string>ADJ_%</string>
        <string>EOP_U</string>
        <string>UNAPPROVED</string>
        <string>MDPROMO_DLR</string>
        <string>SSRATIO</string>
        <string>GMROI</string>
        <string>GM_DLR</string>
        <string>MDTTL_DLR</string>
        <string>MDTTL_%</string>
        <string>Measures</string>
        <string>BOP_AUR</string>
        <string>FWOS</string>
        <string>ACCT2</string>
        <string>SLS_DLR</string>
        <string>COGS_DLR</string>
        <string>BOPIMU_%</string>
        <string>CUM_RECRTL_DLR</string>
        <string>SLSLY_%</string>
        <string>BOPRTL_DLR</string>
        <string>OTBCST_DLR</string>
        <string>REC_AUR</string>
        <string>SLSLY_DLR</string>
        <string>OTBRTL_DLR</string>
        <string>MDPERM_%</string>
        <string>ACCT1</string>
        <string>CUMOTBRTL_DLR</string>
        <string>EOPRTL_APS_DLR</string>
        <string>BOPRTL_APS_DLR</string>
        <string>YTDAVAILCST_DLR</string>
        <string>NEEDED_CUMREC</string>
        <string>SLS_%_PROD_TOT</string>
        <string>APPROVED_TTL</string>
        <string>AUTO</string>
        <string>RTV</string>
        <string>MDCLEAR_%</string>
        <string>OTB_U</string>
        <string>RECIMU_%</string>
        <string>SLS_U</string>
        <string>CUMOTBCST_DLR</string>
      </string-array>
    </entry>
    <entry>
      <string>Product</string>
      <string-array>
        <string>TotProd</string>
        <string>DIV01</string>
        <string>DIV03</string>
        <string>DIV04</string>
        <string>DIV05</string>
        <string>DIV06</string>
        <string>DIV07</string>
        <string>DIV09</string>
        <string>DIV08</string>
        <string>DIV10</string>
      </string-array>
    </entry>
    <entry>
      <string>Version</string>
      <string-array>
        <string>WIF</string>
        <string>WIP</string>
        <string>TY</string>
        <string>SYS</string>
        <string>LLY</string>
        <string>LY</string>
        <string>WP</string>
        <string>WF</string>
        <string>WAP</string>
      </string-array>
    </entry>
    <entry>
      <string>PlanType</string>
      <string-array>
        <string>CorpChn</string>
      </string-array>
    </entry>
    <entry>
      <string>Location</string>
      <string-array>
        <string>StoreTotal</string>
      </string-array>
    </entry>
  </dimMembers>
  <dimensions>
    <string>Measures</string>
    <string>PlanType</string>
    <string>Time</string>
    <string>Version</string>
    <string>Years</string>
    <string>Product</string>
    <string>Location</string>
  </dimensions>
  <axisIndex>
    <entry>
      <int>2</int>
      <string>Time</string>
    </entry>
    <entry>
      <int>4</int>
      <string>Years</string>
    </entry>
    <entry>
      <int>6</int>
      <string>Location</string>
    </entry>
    <entry>
      <int>1</int>
      <string>PlanType</string>
    </entry>
    <entry>
      <int>3</int>
      <string>Version</string>
    </entry>
    <entry>
      <int>5</int>
      <string>Product</string>
    </entry>
    <entry>
      <int>0</int>
      <string>Measures</string>
    </entry>
  </axisIndex>
</com.palladium.paf.app.UnitOfWork>