<ViewSection>
  <name>Product by Location - User Sel Measure vs</name>
  <description></description>
  <primaryFormattingAxis>0</primaryFormattingAxis>
  <readOnly>false</readOnly>
  <managed>false</managed>
  <isEmpty>false</isEmpty>
  <topOffset>0</topOffset>
  <leftOffset>0</leftOffset>
  <scaleUnit>CELL</scaleUnit>
  <pafViewHeaders>
    <ViewHeader>
      <label>Product by Location - User Select Measure</label>
      <globalStyleName>Bold Only</globalStyleName>
    </ViewHeader>
  </pafViewHeaders>
  <rowAxisDims>
    <string>Product</string>
  </rowAxisDims>
  <colAxisDims>
    <string>Location</string>
  </colAxisDims>
  <rowTuples>
    <ViewTuple>
      <headerGlobalStyleName>Header Left 10pt</headerGlobalStyleName>
      <dataBorder>
        <border>32</border>
      </dataBorder>
      <headerBorder>
        <border>32</border>
      </headerBorder>
      <parentFirst>false</parentFirst>
      <axis>0</axis>
      <memberDefs>
        <string>@IDESC(@UOW_ROOT)</string>
      </memberDefs>
    </ViewTuple>
  </rowTuples>
  <colTuples>
    <ViewTuple>
      <headerGlobalStyleName>Header Right 10pt</headerGlobalStyleName>
      <headerBorder>
        <border>32</border>
      </headerBorder>
      <parentFirst>false</parentFirst>
      <axis>1</axis>
      <memberDefs>
        <string>@IDESC(@UOW_ROOT)</string>
      </memberDefs>
    </ViewTuple>
  </colTuples>
  <pageTuples>
    <PageTuple>
      <axis>Measures</axis>
      <member>@USER_SEL(M1)</member>
    </PageTuple>
    <PageTuple>
      <axis>PlanType</axis>
      <member>@UOW_ROOT</member>
    </PageTuple>
    <PageTuple>
      <axis>Time</axis>
      <member>@USER_SEL(T1)</member>
    </PageTuple>
    <PageTuple>
      <axis>Version</axis>
      <member>@PLAN_VERSION</member>
    </PageTuple>
    <PageTuple>
      <axis>Years</axis>
      <member>@UOW_ROOT</member>
    </PageTuple>
  </pageTuples>
  <hierarchyFormatName>LocProd</hierarchyFormatName>
</ViewSection>